[{"title":"Implemented encompassing emulation","author":"Meaghan","date":"2014-05-19-0754","link":"2014-05-19-0754-implemented-encompassing-emulation","tags":["Android","Regex","scope","unicorns"]},{"title":"Integrated bottom-line parallelism","author":"Meaghan","date":"2014-05-22-0433","link":"2014-05-22-0433-integrated-bottom-line-parallelism","tags":["FOSS","kittens","Android","HTML"]},{"title":"Advanced foreground capacity","author":"Meaghan","date":"2014-05-24-0052","link":"2014-05-24-0052-advanced-foreground-capacity","tags":["Photoshop","Android","JavaScript","make"]},{"title":"Streamlined motivating installation","author":"Meaghan","date":"2014-05-25-0400","link":"2014-05-25-0400-streamlined-motivating-installation","tags":["Android","service","PNG","system"]},{"title":"Fundamental cohesive website","author":"Meaghan","date":"2014-05-25-0725","link":"2014-05-25-0725-fundamental-cohesive-website","tags":["inject","search","Android","free"]},{"title":"Devolved exuding circuit","author":"Meaghan","date":"2014-05-25-2144","link":"2014-05-25-2144-devolved-exuding-circuit","tags":["Android","CSS3","beards","IX"]},{"title":"Profound cohesive database","author":"Meaghan","date":"2014-05-28-0051","link":"2014-05-28-0051-profound-cohesive-database","tags":["Android","params","templates","controller"]},{"title":"Re-contextualized system-worthy architecture","author":"Meaghan","date":"2014-05-28-1253","link":"2014-05-28-1253-re-contextualized-system-worthy-architecture","tags":["ES6","Chrome","Android","Angularjs"]},{"title":"Phased transitional benchmark","author":"Meaghan","date":"2014-05-29-0050","link":"2014-05-29-0050-phased-transitional-benchmark","tags":["Android","directive","kittens","JavaScript"]},{"title":"Profound 3rd generation groupware","author":"Meaghan","date":"2014-05-29-1902","link":"2014-05-29-1902-profound-3rd-generation-groupware","tags":["system","Windows","Android","rainbows"]},{"title":"Diverse directional service-desk","author":"Meaghan","date":"2014-05-30-1557","link":"2014-05-30-1557-diverse-directional-service-desk","tags":["NPM","hacks","Android","make"]},{"title":"Synergistic disintermediate knowledge base","author":"Meaghan","date":"2014-06-01-1036","link":"2014-06-01-1036-synergistic-disintermediate-knowledge-base","tags":["PHP","service","search","Android"]},{"title":"Realigned reciprocal support","author":"Meaghan","date":"2014-06-03-0331","link":"2014-06-03-0331-realigned-reciprocal-support","tags":["Android","digest","design"]},{"title":"Integrated dynamic throughput","author":"Meaghan","date":"2014-06-03-0846","link":"2014-06-03-0846-integrated-dynamic-throughput","tags":[2015,"JavaScript","templates","Android"]},{"title":"Multi-lateral well-modulated ability","author":"Meaghan","date":"2014-06-03-1141","link":"2014-06-03-1141-multi-lateral-well-modulated-ability","tags":["Android","service","hacks","unicorns"]},{"title":"Persistent hybrid knowledge base","author":"Meaghan","date":"2014-06-03-1510","link":"2014-06-03-1510-persistent-hybrid-knowledge-base","tags":["Android","PHP","controller","Linux"]},{"title":"Operative well-modulated Graphical User Interface","author":"Meaghan","date":"2014-06-05-0542","link":"2014-06-05-0542-operative-well-modulated-graphical-user-interface","tags":["FOSS","search","Android","Linux"]},{"title":"Switchable explicit collaboration","author":"Meaghan","date":"2014-06-05-1400","link":"2014-06-05-1400-switchable-explicit-collaboration","tags":["IOS","Android","UX","bears"]},{"title":"Multi-channelled holistic product","author":"Meaghan","date":"2014-06-06-0554","link":"2014-06-06-0554-multi-channelled-holistic-product","tags":["Android","graphics","hacks","source"]},{"title":"Grass-roots system-worthy matrix","author":"Meaghan","date":"2014-06-07-1443","link":"2014-06-07-1443-grass-roots-system-worthy-matrix","tags":["JVM","Backbone","ajax","Android"]},{"title":"Advanced national methodology","author":"Meaghan","date":"2014-06-08-1732","link":"2014-06-08-1732-advanced-national-methodology","tags":["UX","Android","OSX","service"]},{"title":"Decentralized zero administration website","author":"Meaghan","date":"2014-06-11-1848","link":"2014-06-11-1848-decentralized-zero-administration-website","tags":["IX","factory","Android","ES6"]},{"title":"Versatile multimedia toolset","author":"Meaghan","date":"2014-06-15-1259","link":"2014-06-15-1259-versatile-multimedia-toolset","tags":["kittens","canvas","Android","Regex"]},{"title":"Configurable global synergy","author":"Meaghan","date":"2014-06-16-0630","link":"2014-06-16-0630-configurable-global-synergy","tags":["CSS3","Backbone","Android","system"]},{"title":"Triple-buffered maximized software","author":"Meaghan","date":"2014-06-16-1332","link":"2014-06-16-1332-triple-buffered-maximized-software","tags":["search","params","Android","CSS"]},{"title":"Switchable non-volatile neural-net","author":"Meaghan","date":"2014-06-17-1752","link":"2014-06-17-1752-switchable-non-volatile-neural-net","tags":["Windows","CSS","source","Android"]},{"title":"Secured modular intranet","author":"Meaghan","date":"2014-06-19-0342","link":"2014-06-19-0342-secured-modular-intranet","tags":["PHP","JavaScript","Android","params"]},{"title":"Proactive dedicated application","author":"Meaghan","date":"2014-06-20-0100","link":"2014-06-20-0100-proactive-dedicated-application","tags":[2015,"system","IX","Android"]},{"title":"Open-source non-volatile forecast","author":"Meaghan","date":"2014-06-21-1759","link":"2014-06-21-1759-open-source-non-volatile-forecast","tags":["Android","OSX","IX","rainbows"]},{"title":"Proactive incremental intranet","author":"Meaghan","date":"2014-06-22-1732","link":"2014-06-22-1732-proactive-incremental-intranet","tags":["Windows","NPM","Android","params"]},{"title":"Robust asynchronous function","author":"Meaghan","date":"2014-06-24-0700","link":"2014-06-24-0700-robust-asynchronous-function","tags":["Android","digest","inject","hacks"]},{"title":"Mandatory 5th generation frame","author":"Meaghan","date":"2014-06-25-1526","link":"2014-06-25-1526-mandatory-5th-generation-frame","tags":["Backbone","Android","unicorns"]},{"title":"Seamless zero administration parallelism","author":"Meaghan","date":"2014-06-27-0059","link":"2014-06-27-0059-seamless-zero-administration-parallelism","tags":["Android","digest","inject","FOSS"]},{"title":"Customer-focused foreground intranet","author":"Meaghan","date":"2014-06-29-0252","link":"2014-06-29-0252-customer-focused-foreground-intranet","tags":["JavaScript","UX","Android","canvas"]},{"title":"Balanced zero defect implementation","author":"Meaghan","date":"2014-06-29-0754","link":"2014-06-29-0754-balanced-zero-defect-implementation","tags":["HTTP","Backbone","Android","Regex"]},{"title":"Profound non-volatile info-mediaries","author":"Meaghan","date":"2014-06-30-1159","link":"2014-06-30-1159-profound-non-volatile-info-mediaries","tags":["Android","premium","PHP","HTML"]},{"title":"Future-proofed tertiary archive","author":"Meaghan","date":"2014-07-04-1055","link":"2014-07-04-1055-future-proofed-tertiary-archive","tags":["OSX","Android","Ember","HTML"]},{"title":"Polarised web-enabled productivity","author":"Meaghan","date":"2014-07-04-2219","link":"2014-07-04-2219-polarised-web-enabled-productivity","tags":["controller","Linux","Android","JVM"]},{"title":"Enhanced 24-7 installation","author":"Meaghan","date":"2014-07-07-0129","link":"2014-07-07-0129-enhanced-24-7-installation","tags":["controller","Android","CSS3","factory"]},{"title":"Down-sized 6th generation time-frame","author":"Meaghan","date":"2014-07-07-2254","link":"2014-07-07-2254-down-sized-6th-generation-time-frame","tags":["Android","hacks","digest","Windows"]},{"title":"Vision-oriented responsive help-desk","author":"Meaghan","date":"2014-07-14-1745","link":"2014-07-14-1745-vision-oriented-responsive-help-desk","tags":["IX","make","Android","service"]},{"title":"Enhanced scalable extranet","author":"Meaghan","date":"2014-07-15-1204","link":"2014-07-15-1204-enhanced-scalable-extranet","tags":["inject","free","Android","system"]},{"title":"Cross-platform disintermediate info-mediaries","author":"Meaghan","date":"2014-07-16-1008","link":"2014-07-16-1008-cross-platform-disintermediate-info-mediaries","tags":["scope","CSS3","Android","Ember"]},{"title":"Cross-group intermediate implementation","author":"Meaghan","date":"2014-07-19-1833","link":"2014-07-19-1833-cross-group-intermediate-implementation","tags":["Ember","rainbows","Linux","Android"]},{"title":"Self-enabling bifurcated concept","author":"Meaghan","date":"2014-07-22-1547","link":"2014-07-22-1547-self-enabling-bifurcated-concept","tags":["SVG","JavaScript","templates","Android"]},{"title":"Triple-buffered client-server open system","author":"Meaghan","date":"2014-07-25-1922","link":"2014-07-25-1922-triple-buffered-client-server-open-system","tags":["Android","templates","ajax","JQuery"]},{"title":"Re-engineered object-oriented intranet","author":"Meaghan","date":"2014-07-26-1111","link":"2014-07-26-1111-re-engineered-object-oriented-intranet","tags":["UX","graphics","Android","ES6"]},{"title":"Realigned mission-critical data-warehouse","author":"Meaghan","date":"2014-07-26-1521","link":"2014-07-26-1521-realigned-mission-critical-data-warehouse","tags":["JavaScript","Android","CSS"]},{"title":"Profit-focused methodical productivity","author":"Meaghan","date":"2014-07-26-1610","link":"2014-07-26-1610-profit-focused-methodical-productivity","tags":["Android","rainbows","Regex"]},{"title":"Quality-focused value-added policy","author":"Meaghan","date":"2014-07-30-1616","link":"2014-07-30-1616-quality-focused-value-added-policy","tags":["NPM","HTML","CSS3","Android"]},{"title":"Devolved modular functionalities","author":"Meaghan","date":"2014-08-03-1740","link":"2014-08-03-1740-devolved-modular-functionalities","tags":["params","scope","Android","UX"]},{"title":"Exclusive regional orchestration","author":"Meaghan","date":"2014-08-04-1802","link":"2014-08-04-1802-exclusive-regional-orchestration","tags":["inject","unicorns","Android","scope"]},{"title":"Re-engineered responsive model","author":"Meaghan","date":"2014-08-06-0858","link":"2014-08-06-0858-re-engineered-responsive-model","tags":["Backbone","make","system","Android"]},{"title":"Synergized tangible function","author":"Meaghan","date":"2014-08-06-1026","link":"2014-08-06-1026-synergized-tangible-function","tags":["Technology","HTML","premium","Android"]},{"title":"Progressive discrete flexibility","author":"Meaghan","date":"2014-08-08-1625","link":"2014-08-08-1625-progressive-discrete-flexibility","tags":["SVG","Android","graphics","search"]},{"title":"Multi-layered value-added protocol","author":"Meaghan","date":"2014-08-09-1334","link":"2014-08-09-1334-multi-layered-value-added-protocol","tags":["IX","HTML","Android","CSS"]},{"title":"Persistent foreground approach","author":"Meaghan","date":"2014-08-09-2349","link":"2014-08-09-2349-persistent-foreground-approach","tags":["HTML5","Android","HTTP"]},{"title":"Robust asymmetric open system","author":"Meaghan","date":"2014-08-10-0658","link":"2014-08-10-0658-robust-asymmetric-open-system","tags":["bears","Android","service","Regex"]},{"title":"Advanced demand-driven frame","author":"Meaghan","date":"2014-08-10-1029","link":"2014-08-10-1029-advanced-demand-driven-frame","tags":[2015,"graphics","Android","FOSS"]},{"title":"Decentralized object-oriented open system","author":"Meaghan","date":"2014-08-10-1538","link":"2014-08-10-1538-decentralized-object-oriented-open-system","tags":["JavaScript","Ember","Android","PNG"]},{"title":"Self-enabling optimizing database","author":"Meaghan","date":"2014-08-10-2144","link":"2014-08-10-2144-self-enabling-optimizing-database","tags":["Android","JVM","make","digest"]},{"title":"Integrated non-volatile framework","author":"Meaghan","date":"2014-08-12-0214","link":"2014-08-12-0214-integrated-non-volatile-framework","tags":["NPM","JavaScript","Android","icons"]},{"title":"Fundamental context-sensitive approach","author":"Meaghan","date":"2014-08-12-0517","link":"2014-08-12-0517-fundamental-context-sensitive-approach","tags":["premium","Windows","Android"]},{"title":"Optimized 24 hour moderator","author":"Meaghan","date":"2014-08-12-1419","link":"2014-08-12-1419-optimized-24-hour-moderator","tags":["Angularjs","Android","search","premium"]},{"title":"Ergonomic exuding approach","author":"Meaghan","date":"2014-08-15-0006","link":"2014-08-15-0006-ergonomic-exuding-approach","tags":["Chrome","Android","HTML5","Technology"]},{"title":"Polarised executive firmware","author":"Meaghan","date":"2014-08-16-1921","link":"2014-08-16-1921-polarised-executive-firmware","tags":["make","rainbows","Android","factory"]},{"title":"Team-oriented regional archive","author":"Meaghan","date":"2014-08-17-0507","link":"2014-08-17-0507-team-oriented-regional-archive","tags":["IX","OSX","Android","JQuery"]},{"title":"Future-proofed static migration","author":"Meaghan","date":"2014-08-17-1144","link":"2014-08-17-1144-future-proofed-static-migration","tags":["PHP","kittens","Android","factory"]},{"title":"Balanced motivating internet solution","author":"Meaghan","date":"2014-08-17-1155","link":"2014-08-17-1155-balanced-motivating-internet-solution","tags":[2015,"Ember","Android","PHP"]},{"title":"Up-sized user-facing policy","author":"Meaghan","date":"2014-08-17-1704","link":"2014-08-17-1704-up-sized-user-facing-policy","tags":["ajax","Android","source","NPM"]},{"title":"Cloned intermediate Graphic Interface","author":"Meaghan","date":"2014-08-17-1742","link":"2014-08-17-1742-cloned-intermediate-graphic-interface","tags":["Android","HTTP","search","canvas"]},{"title":"Pre-emptive zero tolerance groupware","author":"Meaghan","date":"2014-08-18-0730","link":"2014-08-18-0730-pre-emptive-zero-tolerance-groupware","tags":["canvas","controller","search","Android"]},{"title":"Expanded interactive array","author":"Meaghan","date":"2014-08-18-1533","link":"2014-08-18-1533-expanded-interactive-array","tags":["factory","Linux","design","Android"]},{"title":"Diverse actuating extranet","author":"Meaghan","date":"2014-08-19-0304","link":"2014-08-19-0304-diverse-actuating-extranet","tags":["FOSS","templates","Android","JQuery"]},{"title":"Mandatory exuding archive","author":"Meaghan","date":"2014-08-21-1831","link":"2014-08-21-1831-mandatory-exuding-archive","tags":["digest","make","Android","beards"]},{"title":"Intuitive national methodology","author":"Meaghan","date":"2014-08-22-1246","link":"2014-08-22-1246-intuitive-national-methodology","tags":["Angularjs","JavaScript","Android","graphics"]},{"title":"Multi-channelled 6th generation open architecture","author":"Meaghan","date":"2014-08-25-0033","link":"2014-08-25-0033-multi-channelled-6th-generation-open-architecture","tags":["service","JQuery","Android","OSX"]},{"title":"Reverse-engineered modular implementation","author":"Meaghan","date":"2014-08-25-0210","link":"2014-08-25-0210-reverse-engineered-modular-implementation","tags":["search","templates","bears","Android"]},{"title":"Profit-focused even-keeled conglomeration","author":"Meaghan","date":"2014-08-26-1604","link":"2014-08-26-1604-profit-focused-even-keeled-conglomeration","tags":["system","JVM","Android"]},{"title":"Devolved attitude-oriented website","author":"Meaghan","date":"2014-08-27-1918","link":"2014-08-27-1918-devolved-attitude-oriented-website","tags":[2015,"Android","HTML5","beards"]},{"title":"Monitored dedicated help-desk","author":"Meaghan","date":"2014-08-28-1932","link":"2014-08-28-1932-monitored-dedicated-help-desk","tags":["Ember","icons","Android"]},{"title":"Multi-layered 5th generation support","author":"Meaghan","date":"2014-08-29-1739","link":"2014-08-29-1739-multi-layered-5th-generation-support","tags":["HTML","system","NPM","Android"]},{"title":"Networked global functionalities","author":"Meaghan","date":"2014-08-31-1111","link":"2014-08-31-1111-networked-global-functionalities","tags":["PNG","design","Android","source"]},{"title":"Multi-tiered real-time conglomeration","author":"Meaghan","date":"2014-08-31-1534","link":"2014-08-31-1534-multi-tiered-real-time-conglomeration","tags":["Android","HTTP","service","rainbows"]},{"title":"Assimilated foreground intranet","author":"Meaghan","date":"2014-09-04-2303","link":"2014-09-04-2303-assimilated-foreground-intranet","tags":["CSS","service","IX","Android"]},{"title":"User-friendly radical secured line","author":"Meaghan","date":"2014-09-09-0823","link":"2014-09-09-0823-user-friendly-radical-secured-line","tags":["Android","search","unicorns","PNG"]},{"title":"Optional tangible utilisation","author":"Meaghan","date":"2014-09-10-0006","link":"2014-09-10-0006-optional-tangible-utilisation","tags":["Photoshop","IOS","Ember","Android"]},{"title":"Multi-lateral impactful algorithm","author":"Meaghan","date":"2014-09-10-0249","link":"2014-09-10-0249-multi-lateral-impactful-algorithm","tags":["icons","kittens","Android","controller"]},{"title":"Inverse logistical support","author":"Meaghan","date":"2014-09-13-0853","link":"2014-09-13-0853-inverse-logistical-support","tags":["Android","icons","UX","kittens"]},{"title":"Optimized background artificial intelligence","author":"Meaghan","date":"2014-09-14-1752","link":"2014-09-14-1752-optimized-background-artificial-intelligence","tags":["Android","Linux","system","HTML"]},{"title":"Synchronised secondary service-desk","author":"Meaghan","date":"2014-09-18-0048","link":"2014-09-18-0048-synchronised-secondary-service-desk","tags":["inject","Linux","unicorns","Android"]},{"title":"Operative incremental hub","author":"Meaghan","date":"2014-09-18-0120","link":"2014-09-18-0120-operative-incremental-hub","tags":["controller","CSS","Android","kittens"]},{"title":"Cross-platform 3rd generation definition","author":"Meaghan","date":"2014-09-20-2209","link":"2014-09-20-2209-cross-platform-3rd-generation-definition","tags":["system","UX","premium","Android"]},{"title":"Optional executive project","author":"Meaghan","date":"2014-09-23-1337","link":"2014-09-23-1337-optional-executive-project","tags":["bears","Android","service","SVG"]},{"title":"Phased uniform instruction set","author":"Meaghan","date":"2014-09-24-0139","link":"2014-09-24-0139-phased-uniform-instruction-set","tags":["templates","hacks","Android"]},{"title":"Programmable actuating matrices","author":"Meaghan","date":"2014-09-24-0910","link":"2014-09-24-0910-programmable-actuating-matrices","tags":["Android","Technology","directive","HTTP"]},{"title":"Business-focused dedicated core","author":"Meaghan","date":"2014-09-24-1758","link":"2014-09-24-1758-business-focused-dedicated-core","tags":["rainbows","Android","Backbone","Photoshop"]},{"title":"Self-enabling next generation knowledge user","author":"Meaghan","date":"2014-09-28-2302","link":"2014-09-28-2302-self-enabling-next-generation-knowledge-user","tags":["Android","Photoshop","free"]},{"title":"Assimilated 5th generation contingency","author":"Meaghan","date":"2014-09-29-0723","link":"2014-09-29-0723-assimilated-5th-generation-contingency","tags":["ajax","Android","NPM","service"]},{"title":"Versatile dedicated application","author":"Meaghan","date":"2014-10-01-1632","link":"2014-10-01-1632-versatile-dedicated-application","tags":["Android","beards","PNG","IOS"]},{"title":"Mandatory static protocol","author":"Meaghan","date":"2014-10-03-0839","link":"2014-10-03-0839-mandatory-static-protocol","tags":["HTML","Android","UX","search"]},{"title":"Pre-emptive bi-directional core","author":"Meaghan","date":"2014-10-03-1417","link":"2014-10-03-1417-pre-emptive-bi-directional-core","tags":["icons","FOSS","Android","templates"]},{"title":"Business-focused optimal matrix","author":"Meaghan","date":"2014-10-04-0613","link":"2014-10-04-0613-business-focused-optimal-matrix","tags":["inject","JavaScript","Android","system"]},{"title":"Multi-layered background infrastructure","author":"Meaghan","date":"2014-10-06-0300","link":"2014-10-06-0300-multi-layered-background-infrastructure","tags":["SVG","JQuery","UX","Android"]},{"title":"Managed grid-enabled hierarchy","author":"Meaghan","date":"2014-10-06-1807","link":"2014-10-06-1807-managed-grid-enabled-hierarchy","tags":[2015,"FOSS","JVM","Android"]},{"title":"Advanced logistical orchestration","author":"Meaghan","date":"2014-10-08-2025","link":"2014-10-08-2025-advanced-logistical-orchestration","tags":["Photoshop","search","Android"]},{"title":"De-engineered system-worthy standardization","author":"Meaghan","date":"2014-10-10-1434","link":"2014-10-10-1434-de-engineered-system-worthy-standardization","tags":["Android","make","CSS","source"]},{"title":"Enterprise-wide intangible ability","author":"Meaghan","date":"2014-10-10-1948","link":"2014-10-10-1948-enterprise-wide-intangible-ability","tags":["graphics","bears","digest","Android"]},{"title":"Networked asynchronous collaboration","author":"Meaghan","date":"2014-10-12-1244","link":"2014-10-12-1244-networked-asynchronous-collaboration","tags":["Android","rainbows","HTML5","templates"]},{"title":"Cloned clear-thinking core","author":"Meaghan","date":"2014-10-12-1922","link":"2014-10-12-1922-cloned-clear-thinking-core","tags":["directive","Android","ajax","CSS3"]},{"title":"Intuitive incremental structure","author":"Meaghan","date":"2014-10-13-1227","link":"2014-10-13-1227-intuitive-incremental-structure","tags":["JavaScript","free","Android","Technology"]},{"title":"Optional clear-thinking productivity","author":"Meaghan","date":"2014-10-14-0849","link":"2014-10-14-0849-optional-clear-thinking-productivity","tags":["NPM","controller","Android","HTML5"]},{"title":"Customer-focused modular service-desk","author":"Meaghan","date":"2014-10-15-1117","link":"2014-10-15-1117-customer-focused-modular-service-desk","tags":["Technology","Windows","Android","system"]},{"title":"Progressive incremental function","author":"Meaghan","date":"2014-10-17-1718","link":"2014-10-17-1718-progressive-incremental-function","tags":["FOSS","Android","OSX","system"]},{"title":"Triple-buffered tertiary process improvement","author":"Meaghan","date":"2014-10-18-1241","link":"2014-10-18-1241-triple-buffered-tertiary-process-improvement","tags":["Android","digest","FOSS"]},{"title":"Streamlined interactive intranet","author":"Meaghan","date":"2014-10-18-2249","link":"2014-10-18-2249-streamlined-interactive-intranet","tags":["params","PNG","Angularjs","Android"]},{"title":"Right-sized fault-tolerant system engine","author":"Meaghan","date":"2014-10-21-1501","link":"2014-10-21-1501-right-sized-fault-tolerant-system-engine","tags":["templates","search","OSX","Android"]},{"title":"Profound user-facing knowledge user","author":"Meaghan","date":"2014-10-24-1905","link":"2014-10-24-1905-profound-user-facing-knowledge-user","tags":["Android","kittens","HTML","make"]},{"title":"Reduced web-enabled contingency","author":"Meaghan","date":"2014-10-26-0913","link":"2014-10-26-0913-reduced-web-enabled-contingency","tags":["IX","design","Android","make"]},{"title":"Compatible system-worthy access","author":"Meaghan","date":"2014-10-26-1424","link":"2014-10-26-1424-compatible-system-worthy-access","tags":["Android","JVM","Angularjs"]},{"title":"Focused executive system engine","author":"Meaghan","date":"2014-10-27-1820","link":"2014-10-27-1820-focused-executive-system-engine","tags":["Android","scope","CSS","HTTP"]},{"title":"Reactive 6th generation monitoring","author":"Meaghan","date":"2014-10-28-0739","link":"2014-10-28-0739-reactive-6th-generation-monitoring","tags":[2015,"hacks","Android","params"]},{"title":"Optional context-sensitive firmware","author":"Meaghan","date":"2014-10-28-2229","link":"2014-10-28-2229-optional-context-sensitive-firmware","tags":["IX","PNG","Android","CSS"]},{"title":"Function-based asynchronous time-frame","author":"Meaghan","date":"2014-10-30-0301","link":"2014-10-30-0301-function-based-asynchronous-time-frame","tags":["ajax","Ember","JVM","Android"]},{"title":"Stand-alone interactive solution","author":"Meaghan","date":"2014-10-31-1004","link":"2014-10-31-1004-stand-alone-interactive-solution","tags":["Angularjs","FOSS","factory","Android"]},{"title":"Triple-buffered contextually-based software","author":"Meaghan","date":"2014-10-31-1630","link":"2014-10-31-1630-triple-buffered-contextually-based-software","tags":["digest","Android","controller","CSS"]},{"title":"Decentralized client-driven standardization","author":"Meaghan","date":"2014-11-01-0841","link":"2014-11-01-0841-decentralized-client-driven-standardization","tags":["UX","Android","factory","NPM"]},{"title":"Down-sized asymmetric monitoring","author":"Meaghan","date":"2014-11-02-1941","link":"2014-11-02-1941-down-sized-asymmetric-monitoring","tags":["Android","JQuery","make","Backbone"]},{"title":"Reactive radical algorithm","author":"Meaghan","date":"2014-11-05-0821","link":"2014-11-05-0821-reactive-radical-algorithm","tags":["UX","Android","bears","Photoshop"]},{"title":"Synchronised zero administration circuit","author":"Meaghan","date":"2014-11-06-0640","link":"2014-11-06-0640-synchronised-zero-administration-circuit","tags":["Backbone","Android","PHP","unicorns"]},{"title":"Innovative client-server customer loyalty","author":"Meaghan","date":"2014-11-08-1946","link":"2014-11-08-1946-innovative-client-server-customer-loyalty","tags":["premium","Android","Photoshop","UX"]},{"title":"Open-architected mission-critical software","author":"Meaghan","date":"2014-11-11-0350","link":"2014-11-11-0350-open-architected-mission-critical-software","tags":["CSS3","free","Android","unicorns"]},{"title":"Ameliorated stable secured line","author":"Meaghan","date":"2014-11-11-1337","link":"2014-11-11-1337-ameliorated-stable-secured-line","tags":["Android","Chrome","OSX","source"]},{"title":"Inverse 24 hour firmware","author":"Meaghan","date":"2014-11-15-2334","link":"2014-11-15-2334-inverse-24-hour-firmware","tags":["controller","OSX","Android","source"]},{"title":"Organic responsive conglomeration","author":"Meaghan","date":"2014-11-16-0354","link":"2014-11-16-0354-organic-responsive-conglomeration","tags":["Photoshop","Android","service","templates"]},{"title":"Phased maximized help-desk","author":"Meaghan","date":"2014-11-16-0634","link":"2014-11-16-0634-phased-maximized-help-desk","tags":["Android","factory","beards","scope"]},{"title":"Profit-focused value-added application","author":"Meaghan","date":"2014-11-16-2256","link":"2014-11-16-2256-profit-focused-value-added-application","tags":["design","Android","HTML5","JavaScript"]},{"title":"Diverse 24 hour instruction set","author":"Meaghan","date":"2014-11-18-0057","link":"2014-11-18-0057-diverse-24-hour-instruction-set","tags":["Android","digest","JavaScript","inject"]},{"title":"Cross-platform system-worthy middleware","author":"Meaghan","date":"2014-11-18-1047","link":"2014-11-18-1047-cross-platform-system-worthy-middleware","tags":["unicorns","IX","inject","Android"]},{"title":"Decentralized client-server flexibility","author":"Meaghan","date":"2014-11-18-1326","link":"2014-11-18-1326-decentralized-client-server-flexibility","tags":["IOS","Android","scope","HTML5"]},{"title":"Balanced discrete system engine","author":"Meaghan","date":"2014-11-20-0511","link":"2014-11-20-0511-balanced-discrete-system-engine","tags":["digest","controller","Android"]},{"title":"Configurable methodical collaboration","author":"Meaghan","date":"2014-11-20-0649","link":"2014-11-20-0649-configurable-methodical-collaboration","tags":["Android","beards","JQuery","service"]},{"title":"Expanded high-level help-desk","author":"Meaghan","date":"2014-11-20-0919","link":"2014-11-20-0919-expanded-high-level-help-desk","tags":["beards","JavaScript","Android","NPM"]},{"title":"Customer-focused demand-driven groupware","author":"Meaghan","date":"2014-11-23-0923","link":"2014-11-23-0923-customer-focused-demand-driven-groupware","tags":[2015,"JQuery","Android","search"]},{"title":"Configurable directional middleware","author":"Meaghan","date":"2014-11-23-2114","link":"2014-11-23-2114-configurable-directional-middleware","tags":["Android","HTTP","Regex","design"]},{"title":"Fully-configurable 4th generation structure","author":"Meaghan","date":"2014-11-24-0117","link":"2014-11-24-0117-fully-configurable-4th-generation-structure","tags":["premium","Android","JQuery","controller"]},{"title":"Cloned demand-driven extranet","author":"Meaghan","date":"2014-11-24-1240","link":"2014-11-24-1240-cloned-demand-driven-extranet","tags":["HTML","Android","NPM","PHP"]},{"title":"Polarised 24-7 access","author":"Meaghan","date":"2014-11-24-2058","link":"2014-11-24-2058-polarised-24-7-access","tags":["canvas","Android","search","Technology"]},{"title":"Decentralized client-server paradigm","author":"Meaghan","date":"2014-11-25-0631","link":"2014-11-25-0631-decentralized-client-server-paradigm","tags":["graphics","Backbone","design","Android"]},{"title":"Switchable local hardware","author":"Meaghan","date":"2014-11-26-0933","link":"2014-11-26-0933-switchable-local-hardware","tags":["Android","Photoshop","system","PHP"]},{"title":"Exclusive clear-thinking capability","author":"Meaghan","date":"2014-11-27-2340","link":"2014-11-27-2340-exclusive-clear-thinking-capability","tags":["IOS","CSS","Android","Photoshop"]},{"title":"Fully-configurable multi-tasking internet solution","author":"Meaghan","date":"2014-11-29-1141","link":"2014-11-29-1141-fully-configurable-multi-tasking-internet-solution","tags":[2015,"Android","IOS","kittens"]},{"title":"Customer-focused global utilisation","author":"Meaghan","date":"2014-11-30-1545","link":"2014-11-30-1545-customer-focused-global-utilisation","tags":["Android","source","PHP"]},{"title":"Face to face bandwidth-monitored structure","author":"Meaghan","date":"2014-12-02-1336","link":"2014-12-02-1336-face-to-face-bandwidth-monitored-structure","tags":["Android","directive","UX","FOSS"]},{"title":"Focused homogeneous customer loyalty","author":"Meaghan","date":"2014-12-03-1031","link":"2014-12-03-1031-focused-homogeneous-customer-loyalty","tags":["directive","hacks","Ember","Android"]},{"title":"Robust 4th generation workforce","author":"Meaghan","date":"2014-12-05-1709","link":"2014-12-05-1709-robust-4th-generation-workforce","tags":["controller","ajax","bears","Android"]},{"title":"Decentralized high-level hierarchy","author":"Meaghan","date":"2014-12-07-2051","link":"2014-12-07-2051-decentralized-high-level-hierarchy","tags":["design","templates","Android","digest"]},{"title":"Progressive homogeneous software","author":"Meaghan","date":"2014-12-08-0536","link":"2014-12-08-0536-progressive-homogeneous-software","tags":["Photoshop","Android","unicorns"]},{"title":"Robust homogeneous support","author":"Meaghan","date":"2014-12-08-1524","link":"2014-12-08-1524-robust-homogeneous-support","tags":["SVG","Android","HTML","JVM"]},{"title":"Horizontal discrete contingency","author":"Meaghan","date":"2014-12-11-1737","link":"2014-12-11-1737-horizontal-discrete-contingency","tags":["HTML","graphics","Android","service"]},{"title":"Ergonomic radical success","author":"Meaghan","date":"2014-12-12-2218","link":"2014-12-12-2218-ergonomic-radical-success","tags":["CSS3","bears","Android","IOS"]},{"title":"Total background algorithm","author":"Meaghan","date":"2014-12-13-0641","link":"2014-12-13-0641-total-background-algorithm","tags":["HTTP","JQuery","design","Android"]},{"title":"Open-source upward-trending portal","author":"Meaghan","date":"2014-12-13-0943","link":"2014-12-13-0943-open-source-upward-trending-portal","tags":["UX","Android","PNG"]},{"title":"Down-sized bandwidth-monitored collaboration","author":"Meaghan","date":"2014-12-13-1458","link":"2014-12-13-1458-down-sized-bandwidth-monitored-collaboration","tags":["source","NPM","JQuery","Android"]},{"title":"Re-contextualized real-time focus group","author":"Meaghan","date":"2014-12-15-2054","link":"2014-12-15-2054-re-contextualized-real-time-focus-group","tags":["JQuery","Android","icons"]},{"title":"Team-oriented human-resource website","author":"Meaghan","date":"2014-12-16-0923","link":"2014-12-16-0923-team-oriented-human-resource-website","tags":["inject","Android","ES6","service"]},{"title":"Digitized methodical task-force","author":"Meaghan","date":"2014-12-17-1848","link":"2014-12-17-1848-digitized-methodical-task-force","tags":["HTTP","factory","design","Android"]},{"title":"Assimilated fault-tolerant installation","author":"Meaghan","date":"2014-12-18-1403","link":"2014-12-18-1403-assimilated-fault-tolerant-installation","tags":["HTML","Photoshop","HTTP","Android"]},{"title":"Mandatory user-facing open architecture","author":"Meaghan","date":"2014-12-18-2153","link":"2014-12-18-2153-mandatory-user-facing-open-architecture","tags":["system","Photoshop","Android","beards"]},{"title":"Right-sized local algorithm","author":"Meaghan","date":"2014-12-20-1313","link":"2014-12-20-1313-right-sized-local-algorithm","tags":["Technology","CSS3","Android","PHP"]},{"title":"Open-architected national flexibility","author":"Meaghan","date":"2014-12-20-1501","link":"2014-12-20-1501-open-architected-national-flexibility","tags":["Android","rainbows","design","directive"]},{"title":"Reactive discrete structure","author":"Meaghan","date":"2014-12-21-1748","link":"2014-12-21-1748-reactive-discrete-structure","tags":["Photoshop","ES6","bears","Android"]},{"title":"Fundamental eco-centric help-desk","author":"Meaghan","date":"2014-12-22-0125","link":"2014-12-22-0125-fundamental-eco-centric-help-desk","tags":["ajax","Android","IX","free"]},{"title":"Vision-oriented zero defect matrices","author":"Meaghan","date":"2014-12-22-0256","link":"2014-12-22-0256-vision-oriented-zero-defect-matrices","tags":["FOSS","SVG","factory","Android"]},{"title":"Re-engineered fault-tolerant concept","author":"Meaghan","date":"2014-12-22-1434","link":"2014-12-22-1434-re-engineered-fault-tolerant-concept","tags":["premium","canvas","HTML","Android"]},{"title":"Right-sized background focus group","author":"Meaghan","date":"2014-12-24-0544","link":"2014-12-24-0544-right-sized-background-focus-group","tags":["graphics","PHP","scope","Android"]},{"title":"Multi-channelled bifurcated superstructure","author":"Meaghan","date":"2014-12-26-0438","link":"2014-12-26-0438-multi-channelled-bifurcated-superstructure","tags":[2015,"Chrome","params","Android"]},{"title":"Advanced even-keeled local area network","author":"Meaghan","date":"2014-12-26-1546","link":"2014-12-26-1546-advanced-even-keeled-local-area-network","tags":["kittens","Photoshop","CSS3","Android"]},{"title":"Right-sized zero defect contingency","author":"Meaghan","date":"2014-12-27-1730","link":"2014-12-27-1730-right-sized-zero-defect-contingency","tags":["CSS3","params","Android","bears"]},{"title":"Multi-layered secondary contingency","author":"Meaghan","date":"2014-12-28-1317","link":"2014-12-28-1317-multi-layered-secondary-contingency","tags":[2015,"Android","IX","NPM"]},{"title":"Multi-layered bandwidth-monitored model","author":"Meaghan","date":"2014-12-29-0313","link":"2014-12-29-0313-multi-layered-bandwidth-monitored-model","tags":["Android","factory","beards","system"]},{"title":"Implemented reciprocal knowledge user","author":"Meaghan","date":"2014-12-29-0948","link":"2014-12-29-0948-implemented-reciprocal-knowledge-user","tags":["Technology","FOSS","CSS","Android"]},{"title":"Polarised real-time intranet","author":"Meaghan","date":"2014-12-29-0957","link":"2014-12-29-0957-polarised-real-time-intranet","tags":["SVG","premium","Android","factory"]},{"title":"Synergistic regional infrastructure","author":"Meaghan","date":"2014-12-31-0444","link":"2014-12-31-0444-synergistic-regional-infrastructure","tags":["Android","unicorns","inject","free"]},{"title":"Multi-layered non-volatile migration","author":"Meaghan","date":"2015-01-03-0346","link":"2015-01-03-0346-multi-layered-non-volatile-migration","tags":["Technology","icons","OSX","Android"]},{"title":"Assimilated web-enabled Graphic Interface","author":"Meaghan","date":"2015-01-06-0926","link":"2015-01-06-0926-assimilated-web-enabled-graphic-interface","tags":["search","bears","Android","digest"]},{"title":"Expanded web-enabled alliance","author":"Meaghan","date":"2015-01-06-1106","link":"2015-01-06-1106-expanded-web-enabled-alliance","tags":["scope","design","Android","unicorns"]},{"title":"Implemented impactful utilisation","author":"Meaghan","date":"2015-01-06-1437","link":"2015-01-06-1437-implemented-impactful-utilisation","tags":["Android","ES6","params","make"]},{"title":"Profit-focused non-volatile artificial intelligence","author":"Meaghan","date":"2015-01-09-0006","link":"2015-01-09-0006-profit-focused-non-volatile-artificial-intelligence","tags":[2015,"Backbone","Android","Angularjs"]},{"title":"Customizable incremental matrices","author":"Meaghan","date":"2015-01-10-0811","link":"2015-01-10-0811-customizable-incremental-matrices","tags":["CSS","system","Android","factory"]},{"title":"Innovative high-level hierarchy","author":"Meaghan","date":"2015-01-11-0959","link":"2015-01-11-0959-innovative-high-level-hierarchy","tags":["free","graphics","Technology","Android"]},{"title":"Team-oriented solution-oriented system engine","author":"Meaghan","date":"2015-01-11-1851","link":"2015-01-11-1851-team-oriented-solution-oriented-system-engine","tags":["unicorns","make","Android","params"]},{"title":"Synergized 24 hour secured line","author":"Meaghan","date":"2015-01-11-2234","link":"2015-01-11-2234-synergized-24-hour-secured-line","tags":["bears","Android","ES6","service"]},{"title":"Business-focused logistical firmware","author":"Meaghan","date":"2015-01-16-0249","link":"2015-01-16-0249-business-focused-logistical-firmware","tags":["Android","Photoshop","ajax","Angularjs"]},{"title":"Realigned modular structure","author":"Meaghan","date":"2015-01-16-0517","link":"2015-01-16-0517-realigned-modular-structure","tags":[2015,"Android","Backbone","system"]},{"title":"Cross-platform dynamic alliance","author":"Meaghan","date":"2015-01-17-0617","link":"2015-01-17-0617-cross-platform-dynamic-alliance","tags":["hacks","premium","Android","Chrome"]},{"title":"Upgradable solution-oriented collaboration","author":"Meaghan","date":"2015-01-17-1910","link":"2015-01-17-1910-upgradable-solution-oriented-collaboration","tags":["unicorns","Chrome","rainbows","Android"]},{"title":"Object-based content-based forecast","author":"Meaghan","date":"2015-01-19-0330","link":"2015-01-19-0330-object-based-content-based-forecast","tags":["canvas","Android","JavaScript","OSX"]},{"title":"Profound mobile model","author":"Meaghan","date":"2015-01-20-0657","link":"2015-01-20-0657-profound-mobile-model","tags":["params","Android","inject","source"]},{"title":"Customizable explicit contingency","author":"Meaghan","date":"2015-01-20-1414","link":"2015-01-20-1414-customizable-explicit-contingency","tags":["service","CSS3","design","Android"]},{"title":"Enterprise-wide actuating migration","author":"Meaghan","date":"2015-01-20-2231","link":"2015-01-20-2231-enterprise-wide-actuating-migration","tags":["Android","digest","inject","templates"]},{"title":"Virtual cohesive secured line","author":"Meaghan","date":"2015-01-21-0513","link":"2015-01-21-0513-virtual-cohesive-secured-line","tags":["Android","PNG","ES6","bears"]},{"title":"Centralized content-based strategy","author":"Meaghan","date":"2015-01-21-1830","link":"2015-01-21-1830-centralized-content-based-strategy","tags":["inject","JavaScript","Android","OSX"]},{"title":"Upgradable bifurcated local area network","author":"Meaghan","date":"2015-01-22-0650","link":"2015-01-22-0650-upgradable-bifurcated-local-area-network","tags":["premium","NPM","Android","IX"]},{"title":"Polarised 24-7 structure","author":"Meaghan","date":"2015-01-25-0940","link":"2015-01-25-0940-polarised-24-7-structure","tags":[2015,"Android","CSS","kittens"]},{"title":"Proactive systemic success","author":"Meaghan","date":"2015-01-25-1329","link":"2015-01-25-1329-proactive-systemic-success","tags":["Android","CSS","ajax","free"]},{"title":"Seamless leading edge productivity","author":"Meaghan","date":"2015-01-26-1054","link":"2015-01-26-1054-seamless-leading-edge-productivity","tags":["Ember","CSS3","HTTP","Android"]},{"title":"Synergized fresh-thinking intranet","author":"Meaghan","date":"2015-01-31-0513","link":"2015-01-31-0513-synergized-fresh-thinking-intranet","tags":["CSS","HTML","Android","CSS3"]},{"title":"Cross-platform scalable success","author":"Meaghan","date":"2015-02-02-1617","link":"2015-02-02-1617-cross-platform-scalable-success","tags":["design","Android","Regex"]},{"title":"Organized bottom-line challenge","author":"Meaghan","date":"2015-02-03-1211","link":"2015-02-03-1211-organized-bottom-line-challenge","tags":["search","params","Android","HTTP"]},{"title":"Future-proofed intermediate algorithm","author":"Meaghan","date":"2015-02-04-0505","link":"2015-02-04-0505-future-proofed-intermediate-algorithm","tags":["scope","Android","premium","free"]},{"title":"Synergized bottom-line hierarchy","author":"Meaghan","date":"2015-02-04-1543","link":"2015-02-04-1543-synergized-bottom-line-hierarchy","tags":["Technology","Android","NPM","search"]},{"title":"Business-focused full-range process improvement","author":"Meaghan","date":"2015-02-06-1218","link":"2015-02-06-1218-business-focused-full-range-process-improvement","tags":["system","Android","bears","kittens"]},{"title":"Mandatory explicit protocol","author":"Meaghan","date":"2015-02-07-0149","link":"2015-02-07-0149-mandatory-explicit-protocol","tags":["Angularjs","JavaScript","source","Android"]},{"title":"Triple-buffered client-driven neural-net","author":"Meaghan","date":"2015-02-08-2106","link":"2015-02-08-2106-triple-buffered-client-driven-neural-net","tags":["Photoshop","Angularjs","hacks","Android"]},{"title":"Stand-alone multi-tasking paradigm","author":"Meaghan","date":"2015-02-10-1533","link":"2015-02-10-1533-stand-alone-multi-tasking-paradigm","tags":["premium","Android","CSS3","system"]},{"title":"Networked heuristic hierarchy","author":"Meaghan","date":"2015-02-10-2046","link":"2015-02-10-2046-networked-heuristic-hierarchy","tags":["Android","Regex","design","controller"]},{"title":"Ergonomic reciprocal pricing structure","author":"Meaghan","date":"2015-02-12-0147","link":"2015-02-12-0147-ergonomic-reciprocal-pricing-structure","tags":["Android","controller","PNG","graphics"]},{"title":"Front-line didactic contingency","author":"Meaghan","date":"2015-02-12-0214","link":"2015-02-12-0214-front-line-didactic-contingency","tags":["JavaScript","Ember","Android","templates"]},{"title":"Versatile maximized standardization","author":"Meaghan","date":"2015-02-12-1147","link":"2015-02-12-1147-versatile-maximized-standardization","tags":["NPM","source","FOSS","Android"]},{"title":"Secured coherent system engine","author":"Meaghan","date":"2015-02-14-1024","link":"2015-02-14-1024-secured-coherent-system-engine","tags":["controller","free","Android","Windows"]},{"title":"Horizontal neutral ability","author":"Meaghan","date":"2015-02-14-2325","link":"2015-02-14-2325-horizontal-neutral-ability","tags":["scope","Android","Linux","hacks"]},{"title":"Networked upward-trending capacity","author":"Meaghan","date":"2015-02-15-0757","link":"2015-02-15-0757-networked-upward-trending-capacity","tags":["OSX","CSS3","Backbone","Android"]},{"title":"Business-focused zero tolerance help-desk","author":"Meaghan","date":"2015-02-19-1530","link":"2015-02-19-1530-business-focused-zero-tolerance-help-desk","tags":["ajax","PNG","params","Android"]},{"title":"Optional reciprocal migration","author":"Meaghan","date":"2015-02-21-1312","link":"2015-02-21-1312-optional-reciprocal-migration","tags":["Android","FOSS","IOS","JQuery"]},{"title":"Balanced asynchronous framework","author":"Meaghan","date":"2015-02-22-0502","link":"2015-02-22-0502-balanced-asynchronous-framework","tags":["hacks","Android","Linux","IX"]},{"title":"Visionary incremental access","author":"Meaghan","date":"2015-02-23-1907","link":"2015-02-23-1907-visionary-incremental-access","tags":["OSX","Photoshop","Android"]},{"title":"Multi-tiered modular challenge","author":"Meaghan","date":"2015-03-01-1443","link":"2015-03-01-1443-multi-tiered-modular-challenge","tags":["design","graphics","unicorns","Android"]},{"title":"User-friendly didactic focus group","author":"Meaghan","date":"2015-03-02-0722","link":"2015-03-02-0722-user-friendly-didactic-focus-group","tags":["Android","FOSS","kittens","JVM"]},{"title":"Decentralized analyzing orchestration","author":"Meaghan","date":"2015-03-03-1606","link":"2015-03-03-1606-decentralized-analyzing-orchestration","tags":["Linux","OSX","Android","HTML"]},{"title":"Persevering leading edge Graphic Interface","author":"Meaghan","date":"2015-03-05-0049","link":"2015-03-05-0049-persevering-leading-edge-graphic-interface","tags":["Technology","scope","Android","design"]},{"title":"Team-oriented zero administration capacity","author":"Meaghan","date":"2015-03-05-0204","link":"2015-03-05-0204-team-oriented-zero-administration-capacity","tags":["bears","HTML","kittens","Android"]},{"title":"Switchable zero defect instruction set","author":"Meaghan","date":"2015-03-05-2228","link":"2015-03-05-2228-switchable-zero-defect-instruction-set","tags":["Angularjs","Android","system","PHP"]},{"title":"Triple-buffered analyzing ability","author":"Meaghan","date":"2015-03-06-0919","link":"2015-03-06-0919-triple-buffered-analyzing-ability","tags":[2015,"Android","JQuery","ES6"]},{"title":"Synergistic exuding adapter","author":"Meaghan","date":"2015-03-08-0324","link":"2015-03-08-0324-synergistic-exuding-adapter","tags":[2015,"beards","Windows","Android"]},{"title":"Networked full-range moderator","author":"Meaghan","date":"2015-03-08-1202","link":"2015-03-08-1202-networked-full-range-moderator","tags":["SVG","canvas","directive","Android"]},{"title":"Reduced attitude-oriented project","author":"Meaghan","date":"2015-03-08-2017","link":"2015-03-08-2017-reduced-attitude-oriented-project","tags":["params","search","inject","Android"]},{"title":"Grass-roots 4th generation model","author":"Meaghan","date":"2015-03-09-1151","link":"2015-03-09-1151-grass-roots-4th-generation-model","tags":["search","Android","graphics","JavaScript"]},{"title":"Digitized dynamic product","author":"Meaghan","date":"2015-03-09-1303","link":"2015-03-09-1303-digitized-dynamic-product","tags":["JavaScript","Photoshop","NPM","Android"]},{"title":"Customizable maximized secured line","author":"Meaghan","date":"2015-03-11-1130","link":"2015-03-11-1130-customizable-maximized-secured-line","tags":[2015,"directive","HTML5","Android"]},{"title":"De-engineered 24-7 conglomeration","author":"Meaghan","date":"2015-03-12-0044","link":"2015-03-12-0044-de-engineered-24-7-conglomeration","tags":["NPM","Android","JQuery","FOSS"]},{"title":"Profound systematic open system","author":"Meaghan","date":"2015-03-14-0538","link":"2015-03-14-0538-profound-systematic-open-system","tags":["Android","beards","kittens","bears"]},{"title":"Focused even-keeled extranet","author":"Meaghan","date":"2015-03-14-1056","link":"2015-03-14-1056-focused-even-keeled-extranet","tags":["CSS3","controller","Android","HTTP"]},{"title":"Innovative multi-tasking function","author":"Meaghan","date":"2015-03-15-1008","link":"2015-03-15-1008-innovative-multi-tasking-function","tags":["factory","Android","Technology","JVM"]},{"title":"Open-architected 24-7 interface","author":"Meaghan","date":"2015-03-15-2306","link":"2015-03-15-2306-open-architected-24-7-interface","tags":["Android","icons","HTML","HTTP"]},{"title":"Object-based homogeneous support","author":"Meaghan","date":"2015-03-16-1617","link":"2015-03-16-1617-object-based-homogeneous-support","tags":["Android","JQuery","directive","UX"]},{"title":"Profound demand-driven encryption","author":"Meaghan","date":"2015-03-16-2031","link":"2015-03-16-2031-profound-demand-driven-encryption","tags":["PHP","Android","Angularjs","controller"]},{"title":"Integrated attitude-oriented collaboration","author":"Meaghan","date":"2015-03-17-0529","link":"2015-03-17-0529-integrated-attitude-oriented-collaboration","tags":["Android","SVG","hacks","premium"]},{"title":"Cross-platform grid-enabled hub","author":"Meaghan","date":"2015-03-21-1112","link":"2015-03-21-1112-cross-platform-grid-enabled-hub","tags":["Android","params","directive","service"]},{"title":"Focused grid-enabled interface","author":"Meaghan","date":"2015-03-22-0110","link":"2015-03-22-0110-focused-grid-enabled-interface","tags":["Android","Chrome","controller","Windows"]},{"title":"Visionary explicit database","author":"Meaghan","date":"2015-03-22-0332","link":"2015-03-22-0332-visionary-explicit-database","tags":["Android","Linux","unicorns","UX"]},{"title":"De-engineered systemic open system","author":"Meaghan","date":"2015-03-22-0552","link":"2015-03-22-0552-de-engineered-systemic-open-system","tags":["Android","Photoshop","graphics","ajax"]},{"title":"Up-sized explicit capability","author":"Meaghan","date":"2015-03-23-1001","link":"2015-03-23-1001-up-sized-explicit-capability","tags":["rainbows","Android","JQuery","PNG"]},{"title":"Visionary fresh-thinking instruction set","author":"Meaghan","date":"2015-03-23-1304","link":"2015-03-23-1304-visionary-fresh-thinking-instruction-set","tags":["HTML","Android","rainbows","CSS3"]},{"title":"Devolved demand-driven capacity","author":"Meaghan","date":"2015-03-23-2001","link":"2015-03-23-2001-devolved-demand-driven-capacity","tags":["Regex","bears","Android","SVG"]},{"title":"Cloned homogeneous local area network","author":"Meaghan","date":"2015-03-24-2232","link":"2015-03-24-2232-cloned-homogeneous-local-area-network","tags":["Android","Regex","service","inject"]},{"title":"Compatible 6th generation groupware","author":"Meaghan","date":"2015-03-26-0609","link":"2015-03-26-0609-compatible-6th-generation-groupware","tags":["params","Angularjs","PHP","Android"]},{"title":"De-engineered asymmetric approach","author":"Meaghan","date":"2015-03-26-1240","link":"2015-03-26-1240-de-engineered-asymmetric-approach","tags":[2015,"IOS","Android"]},{"title":"Cross-group web-enabled installation","author":"Meaghan","date":"2015-03-28-0749","link":"2015-03-28-0749-cross-group-web-enabled-installation","tags":["Android","search","canvas"]},{"title":"Ameliorated dynamic circuit","author":"Meaghan","date":"2015-03-28-1547","link":"2015-03-28-1547-ameliorated-dynamic-circuit","tags":["free","search","Backbone","Android"]},{"title":"Proactive 6th generation firmware","author":"Meaghan","date":"2015-04-05-1811","link":"2015-04-05-1811-proactive-6th-generation-firmware","tags":["Photoshop","Android","rainbows","Windows"]},{"title":"Business-focused attitude-oriented customer loyalty","author":"Meaghan","date":"2015-04-06-1005","link":"2015-04-06-1005-business-focused-attitude-oriented-customer-loyalty","tags":["Android","NPM","controller","templates"]},{"title":"Optional demand-driven data-warehouse","author":"Meaghan","date":"2015-04-07-1248","link":"2015-04-07-1248-optional-demand-driven-data-warehouse","tags":["JavaScript","inject","beards","Android"]},{"title":"Down-sized full-range capacity","author":"Meaghan","date":"2015-04-08-0109","link":"2015-04-08-0109-down-sized-full-range-capacity","tags":["Android","inject","Angularjs","CSS3"]},{"title":"Fundamental dynamic process improvement","author":"Meaghan","date":"2015-04-08-2118","link":"2015-04-08-2118-fundamental-dynamic-process-improvement","tags":["UX","Backbone","Android","Chrome"]},{"title":"Synergized client-driven groupware","author":"Meaghan","date":"2015-04-09-2127","link":"2015-04-09-2127-synergized-client-driven-groupware","tags":["Android","Ember","ajax","Chrome"]},{"title":"Decentralized interactive software","author":"Meaghan","date":"2015-04-10-0250","link":"2015-04-10-0250-decentralized-interactive-software","tags":["beards","Android","source","kittens"]},{"title":"Compatible tangible framework","author":"Meaghan","date":"2015-04-16-0319","link":"2015-04-16-0319-compatible-tangible-framework","tags":["params","Android","Ember","IX"]},{"title":"Vision-oriented logistical middleware","author":"Meaghan","date":"2015-04-16-1321","link":"2015-04-16-1321-vision-oriented-logistical-middleware","tags":["inject","service","Android","Windows"]},{"title":"Upgradable methodical software","author":"Meaghan","date":"2015-04-16-1849","link":"2015-04-16-1849-upgradable-methodical-software","tags":["CSS","directive","OSX","Android"]},{"title":"Public-key holistic paradigm","author":"Meaghan","date":"2015-04-17-0057","link":"2015-04-17-0057-public-key-holistic-paradigm","tags":["FOSS","Android","PNG"]},{"title":"Automated 3rd generation instruction set","author":"Meaghan","date":"2015-04-17-0614","link":"2015-04-17-0614-automated-3rd-generation-instruction-set","tags":[2015,"HTML","canvas","Android"]},{"title":"Configurable reciprocal intranet","author":"Meaghan","date":"2015-04-18-2236","link":"2015-04-18-2236-configurable-reciprocal-intranet","tags":["graphics","inject","service","Android"]},{"title":"Persevering discrete moderator","author":"Meaghan","date":"2015-04-19-0843","link":"2015-04-19-0843-persevering-discrete-moderator","tags":["PHP","Android","hacks","source"]},{"title":"Open-source clear-thinking capacity","author":"Meaghan","date":"2015-04-21-0021","link":"2015-04-21-0021-open-source-clear-thinking-capacity","tags":["Chrome","IOS","NPM","Android"]},{"title":"Digitized real-time challenge","author":"Meaghan","date":"2015-04-25-1313","link":"2015-04-25-1313-digitized-real-time-challenge","tags":["free","Android","service","ajax"]},{"title":"Re-contextualized dedicated application","author":"Meaghan","date":"2015-04-26-0127","link":"2015-04-26-0127-re-contextualized-dedicated-application","tags":["digest","system","Android","Angularjs"]},{"title":"Cloned interactive Graphical User Interface","author":"Meaghan","date":"2015-04-26-0623","link":"2015-04-26-0623-cloned-interactive-graphical-user-interface","tags":["directive","rainbows","Android","templates"]},{"title":"Organic discrete contingency","author":"Meaghan","date":"2015-04-27-0346","link":"2015-04-27-0346-organic-discrete-contingency","tags":["beards","NPM","Android","JVM"]},{"title":"Universal tertiary circuit","author":"Meaghan","date":"2015-04-27-2342","link":"2015-04-27-2342-universal-tertiary-circuit","tags":["PHP","params","Android","beards"]},{"title":"Streamlined didactic circuit","author":"Meaghan","date":"2015-04-28-1529","link":"2015-04-28-1529-streamlined-didactic-circuit","tags":["Windows","Chrome","CSS","Android"]},{"title":"Pre-emptive contextually-based service-desk","author":"Meaghan","date":"2015-05-01-1727","link":"2015-05-01-1727-pre-emptive-contextually-based-service-desk","tags":["Angularjs","JQuery","source","Android"]},{"title":"Progressive multi-tasking contingency","author":"Meaghan","date":"2015-05-02-2240","link":"2015-05-02-2240-progressive-multi-tasking-contingency","tags":["Ember","Android","source","make"]},{"title":"Pre-emptive eco-centric challenge","author":"Meaghan","date":"2015-05-06-0419","link":"2015-05-06-0419-pre-emptive-eco-centric-challenge","tags":["Android","UX","inject"]},{"title":"Innovative clear-thinking Graphical User Interface","author":"Meaghan","date":"2015-05-09-2134","link":"2015-05-09-2134-innovative-clear-thinking-graphical-user-interface","tags":["Backbone","Android","ajax","JVM"]},{"title":"Switchable motivating task-force","author":"Meaghan","date":"2015-05-11-1142","link":"2015-05-11-1142-switchable-motivating-task-force","tags":["Android","UX","CSS3"]},{"title":"User-centric intangible process improvement","author":"Meaghan","date":"2015-05-13-1622","link":"2015-05-13-1622-user-centric-intangible-process-improvement","tags":["NPM","premium","beards","Android"]},{"title":"Compatible coherent concept","author":"Meaghan","date":"2015-05-15-1205","link":"2015-05-15-1205-compatible-coherent-concept","tags":["JVM","Android","source"]},{"title":"Down-sized responsive circuit","author":"Meaghan","date":"2015-05-18-1133","link":"2015-05-18-1133-down-sized-responsive-circuit","tags":["design","Ember","Android","controller"]}]