{"posts":[{"title":"Re-contextualized directional open architecture","author":"Meaghan","date":"2014-09-27-1225","link":"2014-09-27-1225-re-contextualized-directional-open-architecture","tags":["factory","premium","search","HTTP"]},{"title":"Centralized static array","author":"Meaghan","date":"2014-09-27-1415","link":"2014-09-27-1415-centralized-static-array","tags":["bears","CSS","ES6","scope"]},{"title":"Front-line demand-driven parallelism","author":"Meaghan","date":"2014-09-27-1732","link":"2014-09-27-1732-front-line-demand-driven-parallelism","tags":["HTML5","Angularjs","SVG","Linux"]},{"title":"Proactive even-keeled conglomeration","author":"Meaghan","date":"2014-09-27-2028","link":"2014-09-27-2028-proactive-even-keeled-conglomeration","tags":["PHP","templates","inject","Photoshop"]},{"title":"Persevering tertiary local area network","author":"Meaghan","date":"2014-09-28-0120","link":"2014-09-28-0120-persevering-tertiary-local-area-network","tags":["IOS","Windows","Chrome","controller"]},{"title":"Reduced solution-oriented algorithm","author":"Meaghan","date":"2014-09-28-0301","link":"2014-09-28-0301-reduced-solution-oriented-algorithm","tags":["CSS","hacks","search","inject"]},{"title":"Exclusive 5th generation moratorium","author":"Meaghan","date":"2014-09-28-0827","link":"2014-09-28-0827-exclusive-5th-generation-moratorium","tags":["service","FOSS","icons","JQuery"]},{"title":"Mandatory multi-tasking open system","author":"Meaghan","date":"2014-09-28-1153","link":"2014-09-28-1153-mandatory-multi-tasking-open-system","tags":["HTML5","JQuery","digest","FOSS"]},{"title":"Mandatory zero defect collaboration","author":"Meaghan","date":"2014-09-28-1334","link":"2014-09-28-1334-mandatory-zero-defect-collaboration","tags":["Technology","IOS","Windows","FOSS"]},{"title":"Cross-group 24-7 website","author":"Meaghan","date":"2014-09-28-1657","link":"2014-09-28-1657-cross-group-24-7-website","tags":["ES6","kittens","bears","OSX"]}],"previous":"146","next":"148"}