{"posts":[{"title":"Customer-focused actuating installation","author":"Meaghan","date":"2015-01-27-1539","link":"2015-01-27-1539-customer-focused-actuating-installation","tags":["IOS","kittens","icons","PNG"]},{"title":"Synergistic clear-thinking encryption","author":"Meaghan","date":"2015-01-27-1556","link":"2015-01-27-1556-synergistic-clear-thinking-encryption","tags":["Ember","scope","OSX"]},{"title":"Adaptive well-modulated throughput","author":"Meaghan","date":"2015-01-27-1929","link":"2015-01-27-1929-adaptive-well-modulated-throughput","tags":["rainbows","JVM","IOS","CSS"]},{"title":"Virtual optimizing structure","author":"Meaghan","date":"2015-01-27-1949","link":"2015-01-27-1949-virtual-optimizing-structure","tags":[2015,"HTML","SVG","unicorns"]},{"title":"Networked incremental capacity","author":"Meaghan","date":"2015-01-27-2302","link":"2015-01-27-2302-networked-incremental-capacity","tags":["inject","Technology","kittens","make"]},{"title":"Robust global approach","author":"Meaghan","date":"2015-01-28-0109","link":"2015-01-28-0109-robust-global-approach","tags":[2015,"search","digest","FOSS"]},{"title":"Ergonomic bifurcated artificial intelligence","author":"Meaghan","date":"2015-01-28-0141","link":"2015-01-28-0141-ergonomic-bifurcated-artificial-intelligence","tags":["Photoshop","Technology","CSS","Angularjs"]},{"title":"Programmable global contingency","author":"Meaghan","date":"2015-01-28-0254","link":"2015-01-28-0254-programmable-global-contingency","tags":["HTTP","free","controller","factory"]},{"title":"Right-sized mission-critical product","author":"Meaghan","date":"2015-01-28-0325","link":"2015-01-28-0325-right-sized-mission-critical-product","tags":["HTTP","icons","Regex","PHP"]},{"title":"Horizontal maximized attitude","author":"Meaghan","date":"2015-01-28-0438","link":"2015-01-28-0438-horizontal-maximized-attitude","tags":["JVM","NPM","HTTP","factory"]}],"previous":"278","next":"280"}