{"posts":[{"title":"Proactive homogeneous firmware","author":"Meaghan","date":"2015-02-19-1837","link":"2015-02-19-1837-proactive-homogeneous-firmware","tags":["source","Photoshop","OSX","PHP"]},{"title":"Synergized solution-oriented customer loyalty","author":"Meaghan","date":"2015-02-19-1901","link":"2015-02-19-1901-synergized-solution-oriented-customer-loyalty","tags":["beards","Backbone","JVM","Windows"]},{"title":"Customizable discrete hub","author":"Meaghan","date":"2015-02-19-2237","link":"2015-02-19-2237-customizable-discrete-hub","tags":["Linux","CSS","beards","IX"]},{"title":"Re-contextualized background workforce","author":"Meaghan","date":"2015-02-20-1312","link":"2015-02-20-1312-re-contextualized-background-workforce","tags":["Chrome","free","NPM","premium"]},{"title":"Phased tertiary hub","author":"Meaghan","date":"2015-02-20-1616","link":"2015-02-20-1616-phased-tertiary-hub","tags":["canvas","PNG","bears","CSS3"]},{"title":"Front-line multi-tasking workforce","author":"Meaghan","date":"2015-02-20-1617","link":"2015-02-20-1617-front-line-multi-tasking-workforce","tags":["params","JavaScript","OSX","inject"]},{"title":"Cross-platform radical structure","author":"Meaghan","date":"2015-02-20-2134","link":"2015-02-20-2134-cross-platform-radical-structure","tags":["CSS","IOS","Chrome","HTML"]},{"title":"Reduced zero defect ability","author":"Meaghan","date":"2015-02-20-2224","link":"2015-02-20-2224-reduced-zero-defect-ability","tags":["make","Photoshop","factory","design"]},{"title":"Progressive zero defect matrices","author":"Meaghan","date":"2015-02-21-0502","link":"2015-02-21-0502-progressive-zero-defect-matrices","tags":["factory","kittens","controller","source"]},{"title":"User-friendly 4th generation migration","author":"Meaghan","date":"2015-02-21-0801","link":"2015-02-21-0801-user-friendly-4th-generation-migration","tags":["PNG","Backbone","FOSS","hacks"]}],"previous":"303","next":"305"}