{"posts":[{"title":"Organized dedicated system engine","author":"Meaghan","date":"2015-05-09-2217","link":"2015-05-09-2217-organized-dedicated-system-engine","tags":["make","Photoshop","JQuery"]},{"title":"Future-proofed empowering encoding","author":"Meaghan","date":"2015-05-10-0431","link":"2015-05-10-0431-future-proofed-empowering-encoding","tags":[2015,"icons","controller","SVG"]},{"title":"Seamless bifurcated knowledge base","author":"Meaghan","date":"2015-05-10-0730","link":"2015-05-10-0730-seamless-bifurcated-knowledge-base","tags":["canvas","source","PNG","bears"]},{"title":"Profit-focused regional frame","author":"Meaghan","date":"2015-05-10-0921","link":"2015-05-10-0921-profit-focused-regional-frame","tags":["free","digest","Backbone","service"]},{"title":"Devolved responsive hardware","author":"Meaghan","date":"2015-05-10-0927","link":"2015-05-10-0927-devolved-responsive-hardware","tags":["Windows","PNG","scope","service"]},{"title":"Persistent reciprocal leverage","author":"Meaghan","date":"2015-05-10-0944","link":"2015-05-10-0944-persistent-reciprocal-leverage","tags":["inject","rainbows","design","OSX"]},{"title":"Reactive transitional productivity","author":"Meaghan","date":"2015-05-10-0953","link":"2015-05-10-0953-reactive-transitional-productivity","tags":["CSS","system","JavaScript","free"]},{"title":"Networked heuristic local area network","author":"Meaghan","date":"2015-05-10-1211","link":"2015-05-10-1211-networked-heuristic-local-area-network","tags":[2015,"rainbows","Photoshop","HTML5"]},{"title":"Triple-buffered multi-state open architecture","author":"Meaghan","date":"2015-05-10-1439","link":"2015-05-10-1439-triple-buffered-multi-state-open-architecture","tags":["system","params","Backbone","HTML5"]},{"title":"Fully-configurable tangible emulation","author":"Meaghan","date":"2015-05-10-1821","link":"2015-05-10-1821-fully-configurable-tangible-emulation","tags":["JQuery","factory","PNG","JVM"]}],"previous":"389","next":"391"}